ormar_postgres_full_text/__init__.py
ormar_postgres_full_text/field.py
ormar_postgres_full_text-0.1.0.dist-info/LICENSE
ormar_postgres_full_text-0.1.0.dist-info/WHEEL
ormar_postgres_full_text-0.1.0.dist-info/METADATA
ormar_postgres_full_text-0.1.0.dist-info/RECORD
