Metadata-Version: 2.1
Name: ormar-postgres-full-text
Version: 0.1.0
Summary: Extension to use full text search from postgresql in ormar ORM.
License: MIT
Author: Jegor Kitskerkin
Author-email: jegor.kitskerkin@gmail.com
Requires-Python: >=3.9,<4.0
Classifier: License :: OSI Approved :: MIT License
Classifier: Programming Language :: Python :: 3
Classifier: Programming Language :: Python :: 3.9
Classifier: Programming Language :: Python :: 3.10
Requires-Dist: ormar[postgresql] (==0.11.3)
